pgwebsocket/__init__.py
pgwebsocket/py.typed
pgwebsocket-0.0.1.dist-info/LICENSE
pgwebsocket-0.0.1.dist-info/METADATA
pgwebsocket-0.0.1.dist-info/WHEEL
pgwebsocket-0.0.1.dist-info/top_level.txt
pgwebsocket-0.0.1.dist-info/RECORD
