Metadata-Version: 2.1
Name: pgwebsocket
Version: 0.0.1
Summary: Async websocket to PostgreSQL proxy.
Home-page: UNKNOWN
Author: Barnaby Shearer
Author-email: b@zi.is
License: UNKNOWN
Keywords: postgresql
Platform: UNKNOWN
Classifier: Development Status :: 5 - Production/Stable
Classifier: Programming Language :: Python :: 3
Requires-Python: >=3.7
License-File: LICENSE
Requires-Dist: aiohttp
Requires-Dist: psycopg2
Requires-Dist: types-psycopg2
